{
  "synthetic": [
    {
      "participant_id": "Ethan Taylor",
      "source_type": "synthetic_pilot",
      "age": "19",
      "gender": "Female",
      "student_status": "Gap year",
      "region": "Europe",
      "loneliness_score": "53.6",
      "social_connection_score": "29.2",
      "immediate_reward_bias": "50.0",
      "impulsive_spending_score": "75.0",
      "high_risk_choice_score": "40.0",
      "conflict_defense_score": "55.0",
      "risk_decision_index": "54.5",
      "decision_type": "Balanced decision-maker"
    },
    {
      "participant_id": "Clara Turner",
      "source_type": "synthetic_pilot",
      "age": "23",
      "gender": "Female",
      "student_status": "Undergraduate",
      "region": "Europe",
      "loneliness_score": "82.1",
      "social_connection_score": "8.3",
      "immediate_reward_bias": "66.7",
      "impulsive_spending_score": "80.0",
      "high_risk_choice_score": "40.0",
      "conflict_defense_score": "100.0",
      "risk_decision_index": "68.3",
      "decision_type": "Conflict-defensive responder"
    },
    {
      "participant_id": "Ruby Reed",
      "source_type": "synthetic_pilot",
      "age": "20",
      "gender": "Female",
      "student_status": "Gap year",
      "region": "North America",
      "loneliness_score": "25.0",
      "social_connection_score": "95.8",
      "immediate_reward_bias": "16.7",
      "impulsive_spending_score": "60.0",
      "high_risk_choice_score": "20.0",
      "conflict_defense_score": "35.0",
      "risk_decision_index": "31.1",
      "decision_type": "Social-buffered deliberator"
    },
    {
      "participant_id": "Eli Park",
      "source_type": "synthetic_pilot",
      "age": "17",
      "gender": "Male",
      "student_status": "High school",
      "region": "North America",
      "loneliness_score": "21.4",
      "social_connection_score": "95.8",
      "immediate_reward_bias": "0.0",
      "impulsive_spending_score": "30.0",
      "high_risk_choice_score": "20.0",
      "conflict_defense_score": "30.0",
      "risk_decision_index": "17.0",
      "decision_type": "Social-buffered deliberator"
    },
    {
      "participant_id": "Ethan Wilson",
      "source_type": "synthetic_pilot",
      "age": "19",
      "gender": "Female",
      "student_status": "High school",
      "region": "East Asia",
      "loneliness_score": "50.0",
      "social_connection_score": "83.3",
      "immediate_reward_bias": "50.0",
      "impulsive_spending_score": "70.0",
      "high_risk_choice_score": "60.0",
      "conflict_defense_score": "40.0",
      "risk_decision_index": "56.0",
      "decision_type": "Balanced decision-maker"
    },
    {
      "participant_id": "Ava Kim",
      "source_type": "synthetic_pilot",
      "age": "16",
      "gender": "Male",
      "student_status": "Undergraduate",
      "region": "Europe",
      "loneliness_score": "78.6",
      "social_connection_score": "29.2",
      "immediate_reward_bias": "66.7",
      "impulsive_spending_score": "80.0",
      "high_risk_choice_score": "80.0",
      "conflict_defense_score": "100.0",
      "risk_decision_index": "78.3",
      "decision_type": "Risk-seeking chooser"
    },
    {
      "participant_id": "Noah Evans",
      "source_type": "synthetic_pilot",
      "age": "21",
      "gender": "Female",
      "student_status": "Undergraduate",
      "region": "North America",
      "loneliness_score": "96.4",
      "social_connection_score": "41.7",
      "immediate_reward_bias": "83.3",
      "impulsive_spending_score": "85.0",
      "high_risk_choice_score": "60.0",
      "conflict_defense_score": "95.0",
      "risk_decision_index": "79.7",
      "decision_type": "Reward-sensitive accelerator"
    },
    {
      "participant_id": "Vivian Collins",
      "source_type": "synthetic_pilot",
      "age": "16",
      "gender": "Male",
      "student_status": "Undergraduate",
      "region": "North America",
      "loneliness_score": "0.0",
      "social_connection_score": "91.7",
      "immediate_reward_bias": "33.3",
      "impulsive_spending_score": "5.0",
      "high_risk_choice_score": "60.0",
      "conflict_defense_score": "0.0",
      "risk_decision_index": "27.9",
      "decision_type": "Social-buffered deliberator"
    },
    {
      "participant_id": "Iris Brooks",
      "source_type": "synthetic_pilot",
      "age": "21",
      "gender": "Nonbinary/Other",
      "student_status": "Gap year",
      "region": "East Asia",
      "loneliness_score": "89.3",
      "social_connection_score": "41.7",
      "immediate_reward_bias": "16.7",
      "impulsive_spending_score": "75.0",
      "high_risk_choice_score": "40.0",
      "conflict_defense_score": "75.0",
      "risk_decision_index": "45.8",
      "decision_type": "Conflict-defensive responder"
    },
    {
      "participant_id": "Ella Foster",
      "source_type": "synthetic_pilot",
      "age": "20",
      "gender": "Female",
      "student_status": "Undergraduate",
      "region": "North America",
      "loneliness_score": "78.6",
      "social_connection_score": "37.5",
      "immediate_reward_bias": "66.7",
      "impulsive_spending_score": "65.0",
      "high_risk_choice_score": "40.0",
      "conflict_defense_score": "90.0",
      "risk_decision_index": "63.1",
      "decision_type": "Conflict-defensive responder"
    },
    {
      "participant_id": "Noah Young",
      "source_type": "synthetic_pilot",
      "age": "21",
      "gender": "Female",
      "student_status": "High school",
      "region": "Europe",
      "loneliness_score": "7.1",
      "social_connection_score": "87.5",
      "immediate_reward_bias": "0.0",
      "impulsive_spending_score": "5.0",
      "high_risk_choice_score": "20.0",
      "conflict_defense_score": "45.0",
      "risk_decision_index": "13.0",
      "decision_type": "Social-buffered deliberator"
    },
    {
      "participant_id": "Kai Singh",
      "source_type": "synthetic_pilot",
      "age": "21",
      "gender": "Female",
      "student_status": "Gap year",
      "region": "East Asia",
      "loneliness_score": "28.6",
      "social_connection_score": "79.2",
      "immediate_reward_bias": "16.7",
      "impulsive_spending_score": "45.0",
      "high_risk_choice_score": "20.0",
      "conflict_defense_score": "10.0",
      "risk_decision_index": "23.6",
      "decision_type": "Social-buffered deliberator"
    },
    {
      "participant_id": "Isaac Evans",
      "source_type": "synthetic_pilot",
      "age": "23",
      "gender": "Male",
      "student_status": "High school",
      "region": "North America",
      "loneliness_score": "57.1",
      "social_connection_score": "41.7",
      "immediate_reward_bias": "66.7",
      "impulsive_spending_score": "85.0",
      "high_risk_choice_score": "100.0",
      "conflict_defense_score": "40.0",
      "risk_decision_index": "75.6",
      "decision_type": "Risk-seeking chooser"
    },
    {
      "participant_id": "Maya Ibrahim",
      "source_type": "synthetic_pilot",
      "age": "23",
      "gender": "Male",
      "student_status": "High school",
      "region": "Other",
      "loneliness_score": "60.7",
      "social_connection_score": "66.7",
      "immediate_reward_bias": "66.7",
      "impulsive_spending_score": "55.0",
      "high_risk_choice_score": "60.0",
      "conflict_defense_score": "50.0",
      "risk_decision_index": "59.6",
      "decision_type": "Balanced decision-maker"
    },
    {
      "participant_id": "Naomi Santos",
      "source_type": "synthetic_pilot",
      "age": "18",
      "gender": "Male",
      "student_status": "Undergraduate",
      "region": "Europe",
      "loneliness_score": "32.1",
      "social_connection_score": "20.8",
      "immediate_reward_bias": "33.3",
      "impulsive_spending_score": "35.0",
      "high_risk_choice_score": "60.0",
      "conflict_defense_score": "80.0",
      "risk_decision_index": "47.4",
      "decision_type": "Conflict-defensive responder"
    },
    {
      "participant_id": "Ruby Young",
      "source_type": "synthetic_pilot",
      "age": "20",
      "gender": "Female",
      "student_status": "Undergraduate",
      "region": "North America",
      "loneliness_score": "67.9",
      "social_connection_score": "95.8",
      "immediate_reward_bias": "50.0",
      "impulsive_spending_score": "55.0",
      "high_risk_choice_score": "40.0",
      "conflict_defense_score": "60.0",
      "risk_decision_index": "50.2",
      "decision_type": "Balanced decision-maker"
    },
    {
      "participant_id": "Owen Tan",
      "source_type": "synthetic_pilot",
      "age": "21",
      "gender": "Female",
      "student_status": "Undergraduate",
      "region": "North America",
      "loneliness_score": "42.9",
      "social_connection_score": "79.2",
      "immediate_reward_bias": "33.3",
      "impulsive_spending_score": "40.0",
      "high_risk_choice_score": "20.0",
      "conflict_defense_score": "30.0",
      "risk_decision_index": "31.2",
      "decision_type": "Social-buffered deliberator"
    },
    {
      "participant_id": "Isaac Young",
      "source_type": "synthetic_pilot",
      "age": "18",
      "gender": "Male",
      "student_status": "Gap year",
      "region": "Europe",
      "loneliness_score": "75.0",
      "social_connection_score": "54.2",
      "immediate_reward_bias": "83.3",
      "impulsive_spending_score": "95.0",
      "high_risk_choice_score": "20.0",
      "conflict_defense_score": "70.0",
      "risk_decision_index": "68.4",
      "decision_type": "Reward-sensitive accelerator"
    },
    {
      "participant_id": "Mia Shah",
      "source_type": "synthetic_pilot",
      "age": "19",
      "gender": "Male",
      "student_status": "Undergraduate",
      "region": "North America",
      "loneliness_score": "75.0",
      "social_connection_score": "70.8",
      "immediate_reward_bias": "16.7",
      "impulsive_spending_score": "50.0",
      "high_risk_choice_score": "40.0",
      "conflict_defense_score": "55.0",
      "risk_decision_index": "36.6",
      "decision_type": "Social-buffered deliberator"
    },
    {
      "participant_id": "Felix Shah",
      "source_type": "synthetic_pilot",
      "age": "24",
      "gender": "Female",
      "student_status": "High school",
      "region": "North America",
      "loneliness_score": "10.7",
      "social_connection_score": "91.7",
      "immediate_reward_bias": "0.0",
      "impulsive_spending_score": "0.0",
      "high_risk_choice_score": "20.0",
      "conflict_defense_score": "35.0",
      "risk_decision_index": "10.2",
      "decision_type": "Social-buffered deliberator"
    },
    {
      "participant_id": "Naomi Wilson",
      "source_type": "synthetic_pilot",
      "age": "18",
      "gender": "Male",
      "student_status": "High school",
      "region": "Europe",
      "loneliness_score": "60.7",
      "social_connection_score": "66.7",
      "immediate_reward_bias": "33.3",
      "impulsive_spending_score": "55.0",
      "high_risk_choice_score": "60.0",
      "conflict_defense_score": "40.0",
      "risk_decision_index": "46.4",
      "decision_type": "Balanced decision-maker"
    },
    {
      "participant_id": "Leo Kim",
      "source_type": "synthetic_pilot",
      "age": "21",
      "gender": "Male",
      "student_status": "Undergraduate",
      "region": "Europe",
      "loneliness_score": "85.7",
      "social_connection_score": "29.2",
      "immediate_reward_bias": "66.7",
      "impulsive_spending_score": "85.0",
      "high_risk_choice_score": "40.0",
      "conflict_defense_score": "80.0",
      "risk_decision_index": "66.6",
      "decision_type": "Conflict-defensive responder"
    },
    {
      "participant_id": "Kai Carter",
      "source_type": "synthetic_pilot",
      "age": "17",
      "gender": "Male",
      "student_status": "High school",
      "region": "North America",
      "loneliness_score": "78.6",
      "social_connection_score": "20.8",
      "immediate_reward_bias": "66.7",
      "impulsive_spending_score": "100.0",
      "high_risk_choice_score": "40.0",
      "conflict_defense_score": "100.0",
      "risk_decision_index": "73.3",
      "decision_type": "Conflict-defensive responder"
    },
    {
      "participant_id": "Aria Wilson",
      "source_type": "synthetic_pilot",
      "age": "17",
      "gender": "Male",
      "student_status": "High school",
      "region": "East Asia",
      "loneliness_score": "53.6",
      "social_connection_score": "66.7",
      "immediate_reward_bias": "33.3",
      "impulsive_spending_score": "30.0",
      "high_risk_choice_score": "20.0",
      "conflict_defense_score": "20.0",
      "risk_decision_index": "27.2",
      "decision_type": "Social-buffered deliberator"
    },
    {
      "participant_id": "Caleb Ibrahim",
      "source_type": "synthetic_pilot",
      "age": "21",
      "gender": "Nonbinary/Other",
      "student_status": "Undergraduate",
      "region": "North America",
      "loneliness_score": "10.7",
      "social_connection_score": "83.3",
      "immediate_reward_bias": "16.7",
      "impulsive_spending_score": "25.0",
      "high_risk_choice_score": "40.0",
      "conflict_defense_score": "20.0",
      "risk_decision_index": "25.1",
      "decision_type": "Social-buffered deliberator"
    },
    {
      "participant_id": "Ella Khan",
      "source_type": "synthetic_pilot",
      "age": "18",
      "gender": "Male",
      "student_status": "High school",
      "region": "North America",
      "loneliness_score": "64.3",
      "social_connection_score": "62.5",
      "immediate_reward_bias": "50.0",
      "impulsive_spending_score": "75.0",
      "high_risk_choice_score": "80.0",
      "conflict_defense_score": "75.0",
      "risk_decision_index": "67.5",
      "decision_type": "Risk-seeking chooser"
    },
    {
      "participant_id": "Leah Martinez",
      "source_type": "synthetic_pilot",
      "age": "20",
      "gender": "Female",
      "student_status": "Undergraduate",
      "region": "North America",
      "loneliness_score": "67.9",
      "social_connection_score": "83.3",
      "immediate_reward_bias": "83.3",
      "impulsive_spending_score": "100.0",
      "high_risk_choice_score": "20.0",
      "conflict_defense_score": "80.0",
      "risk_decision_index": "71.2",
      "decision_type": "Reward-sensitive accelerator"
    },
    {
      "participant_id": "Maya Brooks",
      "source_type": "synthetic_pilot",
      "age": "18",
      "gender": "Male",
      "student_status": "Undergraduate",
      "region": "East Asia",
      "loneliness_score": "35.7",
      "social_connection_score": "66.7",
      "immediate_reward_bias": "33.3",
      "impulsive_spending_score": "50.0",
      "high_risk_choice_score": "40.0",
      "conflict_defense_score": "55.0",
      "risk_decision_index": "42.4",
      "decision_type": "Balanced decision-maker"
    },
    {
      "participant_id": "Ella Rivera",
      "source_type": "synthetic_pilot",
      "age": "18",
      "gender": "Female",
      "student_status": "Undergraduate",
      "region": "North America",
      "loneliness_score": "96.4",
      "social_connection_score": "12.5",
      "immediate_reward_bias": "83.3",
      "impulsive_spending_score": "60.0",
      "high_risk_choice_score": "80.0",
      "conflict_defense_score": "85.0",
      "risk_decision_index": "76.9",
      "decision_type": "Reward-sensitive accelerator"
    },
    {
      "participant_id": "Jasper Liu",
      "source_type": "synthetic_pilot",
      "age": "18",
      "gender": "Male",
      "student_status": "Undergraduate",
      "region": "Europe",
      "loneliness_score": "17.9",
      "social_connection_score": "100.0",
      "immediate_reward_bias": "16.7",
      "impulsive_spending_score": "40.0",
      "high_risk_choice_score": "0.0",
      "conflict_defense_score": "0.0",
      "risk_decision_index": "15.8",
      "decision_type": "Social-buffered deliberator"
    },
    {
      "participant_id": "Clara Garcia",
      "source_type": "synthetic_pilot",
      "age": "21",
      "gender": "Female",
      "student_status": "Undergraduate",
      "region": "North America",
      "loneliness_score": "89.3",
      "social_connection_score": "16.7",
      "immediate_reward_bias": "83.3",
      "impulsive_spending_score": "85.0",
      "high_risk_choice_score": "60.0",
      "conflict_defense_score": "75.0",
      "risk_decision_index": "76.7",
      "decision_type": "Reward-sensitive accelerator"
    },
    {
      "participant_id": "Grace Collins",
      "source_type": "synthetic_pilot",
      "age": "17",
      "gender": "Male",
      "student_status": "High school",
      "region": "North America",
      "loneliness_score": "60.7",
      "social_connection_score": "41.7",
      "immediate_reward_bias": "50.0",
      "impulsive_spending_score": "60.0",
      "high_risk_choice_score": "20.0",
      "conflict_defense_score": "85.0",
      "risk_decision_index": "50.2",
      "decision_type": "Conflict-defensive responder"
    },
    {
      "participant_id": "Isaac Martinez",
      "source_type": "synthetic_pilot",
      "age": "23",
      "gender": "Male",
      "student_status": "Gap year",
      "region": "North America",
      "loneliness_score": "82.1",
      "social_connection_score": "58.3",
      "immediate_reward_bias": "33.3",
      "impulsive_spending_score": "95.0",
      "high_risk_choice_score": "80.0",
      "conflict_defense_score": "50.0",
      "risk_decision_index": "62.9",
      "decision_type": "Risk-seeking chooser"
    },
    {
      "participant_id": "Isaac Hughes",
      "source_type": "synthetic_pilot",
      "age": "19",
      "gender": "Female",
      "student_status": "High school",
      "region": "North America",
      "loneliness_score": "78.6",
      "social_connection_score": "8.3",
      "immediate_reward_bias": "83.3",
      "impulsive_spending_score": "65.0",
      "high_risk_choice_score": "80.0",
      "conflict_defense_score": "60.0",
      "risk_decision_index": "74.4",
      "decision_type": "Reward-sensitive accelerator"
    },
    {
      "participant_id": "Aria Liu",
      "source_type": "synthetic_pilot",
      "age": "18",
      "gender": "Female",
      "student_status": "High school",
      "region": "Europe",
      "loneliness_score": "60.7",
      "social_connection_score": "62.5",
      "immediate_reward_bias": "16.7",
      "impulsive_spending_score": "50.0",
      "high_risk_choice_score": "60.0",
      "conflict_defense_score": "85.0",
      "risk_decision_index": "46.1",
      "decision_type": "Conflict-defensive responder"
    },
    {
      "participant_id": "Jasper Collins",
      "source_type": "synthetic_pilot",
      "age": "17",
      "gender": "Male",
      "student_status": "High school",
      "region": "East Asia",
      "loneliness_score": "67.9",
      "social_connection_score": "33.3",
      "immediate_reward_bias": "50.0",
      "impulsive_spending_score": "100.0",
      "high_risk_choice_score": "20.0",
      "conflict_defense_score": "70.0",
      "risk_decision_index": "58.0",
      "decision_type": "Conflict-defensive responder"
    },
    {
      "participant_id": "Ryan Mehta",
      "source_type": "synthetic_pilot",
      "age": "16",
      "gender": "Male",
      "student_status": "Early career",
      "region": "North America",
      "loneliness_score": "39.3",
      "social_connection_score": "83.3",
      "immediate_reward_bias": "50.0",
      "impulsive_spending_score": "30.0",
      "high_risk_choice_score": "20.0",
      "conflict_defense_score": "65.0",
      "risk_decision_index": "39.8",
      "decision_type": "Conflict-defensive responder"
    },
    {
      "participant_id": "Luna Santos",
      "source_type": "synthetic_pilot",
      "age": "16",
      "gender": "Male",
      "student_status": "High school",
      "region": "East Asia",
      "loneliness_score": "21.4",
      "social_connection_score": "83.3",
      "immediate_reward_bias": "0.0",
      "impulsive_spending_score": "25.0",
      "high_risk_choice_score": "0.0",
      "conflict_defense_score": "20.0",
      "risk_decision_index": "9.2",
      "decision_type": "Social-buffered deliberator"
    },
    {
      "participant_id": "Owen Young",
      "source_type": "synthetic_pilot",
      "age": "17",
      "gender": "Male",
      "student_status": "Undergraduate",
      "region": "Europe",
      "loneliness_score": "35.7",
      "social_connection_score": "66.7",
      "immediate_reward_bias": "0.0",
      "impulsive_spending_score": "55.0",
      "high_risk_choice_score": "20.0",
      "conflict_defense_score": "5.0",
      "risk_decision_index": "19.5",
      "decision_type": "Social-buffered deliberator"
    },
    {
      "participant_id": "Ethan Rossi",
      "source_type": "synthetic_pilot",
      "age": "20",
      "gender": "Male",
      "student_status": "High school",
      "region": "Europe",
      "loneliness_score": "35.7",
      "social_connection_score": "58.3",
      "immediate_reward_bias": "0.0",
      "impulsive_spending_score": "80.0",
      "high_risk_choice_score": "40.0",
      "conflict_defense_score": "55.0",
      "risk_decision_index": "38.2",
      "decision_type": "Balanced decision-maker"
    },
    {
      "participant_id": "Ethan Collins",
      "source_type": "synthetic_pilot",
      "age": "16",
      "gender": "Male",
      "student_status": "Undergraduate",
      "region": "East Asia",
      "loneliness_score": "35.7",
      "social_connection_score": "75.0",
      "immediate_reward_bias": "16.7",
      "impulsive_spending_score": "50.0",
      "high_risk_choice_score": "0.0",
      "conflict_defense_score": "25.0",
      "risk_decision_index": "22.1",
      "decision_type": "Social-buffered deliberator"
    },
    {
      "participant_id": "Felix Wang",
      "source_type": "synthetic_pilot",
      "age": "19",
      "gender": "Male",
      "student_status": "High school",
      "region": "East Asia",
      "loneliness_score": "85.7",
      "social_connection_score": "66.7",
      "immediate_reward_bias": "33.3",
      "impulsive_spending_score": "80.0",
      "high_risk_choice_score": "60.0",
      "conflict_defense_score": "60.0",
      "risk_decision_index": "55.7",
      "decision_type": "Balanced decision-maker"
    },
    {
      "participant_id": "Maya Reed",
      "source_type": "synthetic_pilot",
      "age": "23",
      "gender": "Female",
      "student_status": "Early career",
      "region": "North America",
      "loneliness_score": "50.0",
      "social_connection_score": "91.7",
      "immediate_reward_bias": "33.3",
      "impulsive_spending_score": "35.0",
      "high_risk_choice_score": "40.0",
      "conflict_defense_score": "55.0",
      "risk_decision_index": "38.7",
      "decision_type": "Balanced decision-maker"
    },
    {
      "participant_id": "Nina Park",
      "source_type": "synthetic_pilot",
      "age": "21",
      "gender": "Male",
      "student_status": "Undergraduate",
      "region": "North America",
      "loneliness_score": "21.4",
      "social_connection_score": "95.8",
      "immediate_reward_bias": "33.3",
      "impulsive_spending_score": "65.0",
      "high_risk_choice_score": "0.0",
      "conflict_defense_score": "10.0",
      "risk_decision_index": "29.4",
      "decision_type": "Social-buffered deliberator"
    },
    {
      "participant_id": "Naomi Khan",
      "source_type": "synthetic_pilot",
      "age": "17",
      "gender": "Male",
      "student_status": "High school",
      "region": "Other",
      "loneliness_score": "57.1",
      "social_connection_score": "83.3",
      "immediate_reward_bias": "33.3",
      "impulsive_spending_score": "50.0",
      "high_risk_choice_score": "0.0",
      "conflict_defense_score": "45.0",
      "risk_decision_index": "30.9",
      "decision_type": "Social-buffered deliberator"
    },
    {
      "participant_id": "Jasper Hassan",
      "source_type": "synthetic_pilot",
      "age": "20",
      "gender": "Female",
      "student_status": "High school",
      "region": "Europe",
      "loneliness_score": "32.1",
      "social_connection_score": "83.3",
      "immediate_reward_bias": "50.0",
      "impulsive_spending_score": "70.0",
      "high_risk_choice_score": "40.0",
      "conflict_defense_score": "35.0",
      "risk_decision_index": "50.2",
      "decision_type": "Balanced decision-maker"
    },
    {
      "participant_id": "Lucas Lin",
      "source_type": "synthetic_pilot",
      "age": "21",
      "gender": "Male",
      "student_status": "High school",
      "region": "Europe",
      "loneliness_score": "100.0",
      "social_connection_score": "25.0",
      "immediate_reward_bias": "83.3",
      "impulsive_spending_score": "100.0",
      "high_risk_choice_score": "40.0",
      "conflict_defense_score": "90.0",
      "risk_decision_index": "77.7",
      "decision_type": "Reward-sensitive accelerator"
    },
    {
      "participant_id": "Jasper Murphy",
      "source_type": "synthetic_pilot",
      "age": "19",
      "gender": "Male",
      "student_status": "Early career",
      "region": "North America",
      "loneliness_score": "28.6",
      "social_connection_score": "75.0",
      "immediate_reward_bias": "16.7",
      "impulsive_spending_score": "25.0",
      "high_risk_choice_score": "40.0",
      "conflict_defense_score": "10.0",
      "risk_decision_index": "23.6",
      "decision_type": "Social-buffered deliberator"
    },
    {
      "participant_id": "Sofia Walker",
      "source_type": "synthetic_pilot",
      "age": "19",
      "gender": "Female",
      "student_status": "Undergraduate",
      "region": "North America",
      "loneliness_score": "42.9",
      "social_connection_score": "79.2",
      "immediate_reward_bias": "33.3",
      "impulsive_spending_score": "80.0",
      "high_risk_choice_score": "40.0",
      "conflict_defense_score": "15.0",
      "risk_decision_index": "43.9",
      "decision_type": "Balanced decision-maker"
    },
    {
      "participant_id": "Theo Foster",
      "source_type": "synthetic_pilot",
      "age": "20",
      "gender": "Male",
      "student_status": "Undergraduate",
      "region": "East Asia",
      "loneliness_score": "100.0",
      "social_connection_score": "16.7",
      "immediate_reward_bias": "50.0",
      "impulsive_spending_score": "100.0",
      "high_risk_choice_score": "60.0",
      "conflict_defense_score": "100.0",
      "risk_decision_index": "72.5",
      "decision_type": "Conflict-defensive responder"
    },
    {
      "participant_id": "Leah Morgan",
      "source_type": "synthetic_pilot",
      "age": "18",
      "gender": "Male",
      "student_status": "High school",
      "region": "Europe",
      "loneliness_score": "53.6",
      "social_connection_score": "37.5",
      "immediate_reward_bias": "33.3",
      "impulsive_spending_score": "85.0",
      "high_risk_choice_score": "60.0",
      "conflict_defense_score": "55.0",
      "risk_decision_index": "56.2",
      "decision_type": "Balanced decision-maker"
    },
    {
      "participant_id": "Noah Torres",
      "source_type": "synthetic_pilot",
      "age": "16",
      "gender": "Male",
      "student_status": "Undergraduate",
      "region": "East Asia",
      "loneliness_score": "67.9",
      "social_connection_score": "37.5",
      "immediate_reward_bias": "33.3",
      "impulsive_spending_score": "70.0",
      "high_risk_choice_score": "20.0",
      "conflict_defense_score": "35.0",
      "risk_decision_index": "39.4",
      "decision_type": "Balanced decision-maker"
    },
    {
      "participant_id": "Nina Garcia",
      "source_type": "synthetic_pilot",
      "age": "18",
      "gender": "Female",
      "student_status": "Early career",
      "region": "North America",
      "loneliness_score": "96.4",
      "social_connection_score": "0.0",
      "immediate_reward_bias": "100.0",
      "impulsive_spending_score": "95.0",
      "high_risk_choice_score": "60.0",
      "conflict_defense_score": "100.0",
      "risk_decision_index": "88.8",
      "decision_type": "Reward-sensitive accelerator"
    },
    {
      "participant_id": "Hannah Kim",
      "source_type": "synthetic_pilot",
      "age": "20",
      "gender": "Male",
      "student_status": "Undergraduate",
      "region": "North America",
      "loneliness_score": "42.9",
      "social_connection_score": "58.3",
      "immediate_reward_bias": "33.3",
      "impulsive_spending_score": "40.0",
      "high_risk_choice_score": "80.0",
      "conflict_defense_score": "70.0",
      "risk_decision_index": "52.2",
      "decision_type": "Risk-seeking chooser"
    },
    {
      "participant_id": "Emma Khan",
      "source_type": "synthetic_pilot",
      "age": "16",
      "gender": "Male",
      "student_status": "Gap year",
      "region": "Other",
      "loneliness_score": "57.1",
      "social_connection_score": "37.5",
      "immediate_reward_bias": "66.7",
      "impulsive_spending_score": "25.0",
      "high_risk_choice_score": "100.0",
      "conflict_defense_score": "70.0",
      "risk_decision_index": "65.1",
      "decision_type": "Risk-seeking chooser"
    },
    {
      "participant_id": "Mia Rossi",
      "source_type": "synthetic_pilot",
      "age": "18",
      "gender": "Male",
      "student_status": "High school",
      "region": "North America",
      "loneliness_score": "32.1",
      "social_connection_score": "50.0",
      "immediate_reward_bias": "16.7",
      "impulsive_spending_score": "90.0",
      "high_risk_choice_score": "40.0",
      "conflict_defense_score": "60.0",
      "risk_decision_index": "47.3",
      "decision_type": "Balanced decision-maker"
    },
    {
      "participant_id": "Aria Bennett",
      "source_type": "synthetic_pilot",
      "age": "18",
      "gender": "Male",
      "student_status": "Undergraduate",
      "region": "East Asia",
      "loneliness_score": "89.3",
      "social_connection_score": "12.5",
      "immediate_reward_bias": "50.0",
      "impulsive_spending_score": "65.0",
      "high_risk_choice_score": "40.0",
      "conflict_defense_score": "85.0",
      "risk_decision_index": "56.5",
      "decision_type": "Conflict-defensive responder"
    },
    {
      "participant_id": "Owen Mehta",
      "source_type": "synthetic_pilot",
      "age": "22",
      "gender": "Male",
      "student_status": "Early career",
      "region": "North America",
      "loneliness_score": "28.6",
      "social_connection_score": "100.0",
      "immediate_reward_bias": "0.0",
      "impulsive_spending_score": "40.0",
      "high_risk_choice_score": "0.0",
      "conflict_defense_score": "40.0",
      "risk_decision_index": "16.0",
      "decision_type": "Social-buffered deliberator"
    },
    {
      "participant_id": "Vivian Shah",
      "source_type": "synthetic_pilot",
      "age": "18",
      "gender": "Female",
      "student_status": "High school",
      "region": "North America",
      "loneliness_score": "85.7",
      "social_connection_score": "29.2",
      "immediate_reward_bias": "83.3",
      "impulsive_spending_score": "40.0",
      "high_risk_choice_score": "40.0",
      "conflict_defense_score": "70.0",
      "risk_decision_index": "59.7",
      "decision_type": "Conflict-defensive responder"
    },
    {
      "participant_id": "Felix Rossi",
      "source_type": "synthetic_pilot",
      "age": "18",
      "gender": "Female",
      "student_status": "High school",
      "region": "North America",
      "loneliness_score": "60.7",
      "social_connection_score": "79.2",
      "immediate_reward_bias": "50.0",
      "impulsive_spending_score": "85.0",
      "high_risk_choice_score": "40.0",
      "conflict_defense_score": "70.0",
      "risk_decision_index": "59.2",
      "decision_type": "Conflict-defensive responder"
    },
    {
      "participant_id": "Julian Taylor",
      "source_type": "synthetic_pilot",
      "age": "18",
      "gender": "Male",
      "student_status": "High school",
      "region": "North America",
      "loneliness_score": "42.9",
      "social_connection_score": "41.7",
      "immediate_reward_bias": "33.3",
      "impulsive_spending_score": "55.0",
      "high_risk_choice_score": "60.0",
      "conflict_defense_score": "60.0",
      "risk_decision_index": "49.4",
      "decision_type": "Balanced decision-maker"
    },
    {
      "participant_id": "Adrian Nguyen",
      "source_type": "synthetic_pilot",
      "age": "18",
      "gender": "Female",
      "student_status": "Undergraduate",
      "region": "North America",
      "loneliness_score": "7.1",
      "social_connection_score": "87.5",
      "immediate_reward_bias": "16.7",
      "impulsive_spending_score": "40.0",
      "high_risk_choice_score": "20.0",
      "conflict_defense_score": "35.0",
      "risk_decision_index": "26.1",
      "decision_type": "Social-buffered deliberator"
    },
    {
      "participant_id": "Lucas Rivera",
      "source_type": "synthetic_pilot",
      "age": "24",
      "gender": "Female",
      "student_status": "High school",
      "region": "North America",
      "loneliness_score": "46.4",
      "social_connection_score": "45.8",
      "immediate_reward_bias": "16.7",
      "impulsive_spending_score": "45.0",
      "high_risk_choice_score": "40.0",
      "conflict_defense_score": "55.0",
      "risk_decision_index": "35.3",
      "decision_type": "Balanced decision-maker"
    },
    {
      "participant_id": "Mia Patel",
      "source_type": "synthetic_pilot",
      "age": "23",
      "gender": "Female",
      "student_status": "Early career",
      "region": "North America",
      "loneliness_score": "17.9",
      "social_connection_score": "100.0",
      "immediate_reward_bias": "16.7",
      "impulsive_spending_score": "10.0",
      "high_risk_choice_score": "0.0",
      "conflict_defense_score": "5.0",
      "risk_decision_index": "9.1",
      "decision_type": "Social-buffered deliberator"
    },
    {
      "participant_id": "Ella Lopez",
      "source_type": "synthetic_pilot",
      "age": "24",
      "gender": "Female",
      "student_status": "High school",
      "region": "North America",
      "loneliness_score": "60.7",
      "social_connection_score": "58.3",
      "immediate_reward_bias": "83.3",
      "impulsive_spending_score": "85.0",
      "high_risk_choice_score": "60.0",
      "conflict_defense_score": "65.0",
      "risk_decision_index": "75.2",
      "decision_type": "Reward-sensitive accelerator"
    },
    {
      "participant_id": "Emma Zhang",
      "source_type": "synthetic_pilot",
      "age": "22",
      "gender": "Female",
      "student_status": "Undergraduate",
      "region": "East Asia",
      "loneliness_score": "46.4",
      "social_connection_score": "41.7",
      "immediate_reward_bias": "50.0",
      "impulsive_spending_score": "30.0",
      "high_risk_choice_score": "0.0",
      "conflict_defense_score": "40.0",
      "risk_decision_index": "31.0",
      "decision_type": "Balanced decision-maker"
    },
    {
      "participant_id": "Nora Foster",
      "source_type": "synthetic_pilot",
      "age": "17",
      "gender": "Female",
      "student_status": "Undergraduate",
      "region": "North America",
      "loneliness_score": "46.4",
      "social_connection_score": "66.7",
      "immediate_reward_bias": "33.3",
      "impulsive_spending_score": "80.0",
      "high_risk_choice_score": "40.0",
      "conflict_defense_score": "30.0",
      "risk_decision_index": "46.2",
      "decision_type": "Balanced decision-maker"
    },
    {
      "participant_id": "Clara Evans",
      "source_type": "synthetic_pilot",
      "age": "23",
      "gender": "Male",
      "student_status": "High school",
      "region": "North America",
      "loneliness_score": "42.9",
      "social_connection_score": "62.5",
      "immediate_reward_bias": "33.3",
      "impulsive_spending_score": "65.0",
      "high_risk_choice_score": "40.0",
      "conflict_defense_score": "35.0",
      "risk_decision_index": "43.2",
      "decision_type": "Balanced decision-maker"
    },
    {
      "participant_id": "Felix Garcia",
      "source_type": "synthetic_pilot",
      "age": "19",
      "gender": "Prefer not to say",
      "student_status": "Gap year",
      "region": "North America",
      "loneliness_score": "78.6",
      "social_connection_score": "75.0",
      "immediate_reward_bias": "33.3",
      "impulsive_spending_score": "70.0",
      "high_risk_choice_score": "20.0",
      "conflict_defense_score": "45.0",
      "risk_decision_index": "40.9",
      "decision_type": "Balanced decision-maker"
    },
    {
      "participant_id": "Caleb Ali",
      "source_type": "synthetic_pilot",
      "age": "24",
      "gender": "Female",
      "student_status": "Undergraduate",
      "region": "North America",
      "loneliness_score": "35.7",
      "social_connection_score": "83.3",
      "immediate_reward_bias": "50.0",
      "impulsive_spending_score": "60.0",
      "high_risk_choice_score": "40.0",
      "conflict_defense_score": "50.0",
      "risk_decision_index": "50.0",
      "decision_type": "Balanced decision-maker"
    },
    {
      "participant_id": "Grace Patel",
      "source_type": "synthetic_pilot",
      "age": "19",
      "gender": "Female",
      "student_status": "High school",
      "region": "North America",
      "loneliness_score": "10.7",
      "social_connection_score": "62.5",
      "immediate_reward_bias": "33.3",
      "impulsive_spending_score": "55.0",
      "high_risk_choice_score": "0.0",
      "conflict_defense_score": "10.0",
      "risk_decision_index": "26.9",
      "decision_type": "Social-buffered deliberator"
    },
    {
      "participant_id": "Ryan Rossi",
      "source_type": "synthetic_pilot",
      "age": "21",
      "gender": "Male",
      "student_status": "Early career",
      "region": "North America",
      "loneliness_score": "32.1",
      "social_connection_score": "54.2",
      "immediate_reward_bias": "66.7",
      "impulsive_spending_score": "25.0",
      "high_risk_choice_score": "0.0",
      "conflict_defense_score": "25.0",
      "risk_decision_index": "33.3",
      "decision_type": "Balanced decision-maker"
    },
    {
      "participant_id": "Leo Garcia",
      "source_type": "synthetic_pilot",
      "age": "20",
      "gender": "Female",
      "student_status": "High school",
      "region": "North America",
      "loneliness_score": "64.3",
      "social_connection_score": "50.0",
      "immediate_reward_bias": "33.3",
      "impulsive_spending_score": "45.0",
      "high_risk_choice_score": "60.0",
      "conflict_defense_score": "40.0",
      "risk_decision_index": "43.9",
      "decision_type": "Balanced decision-maker"
    },
    {
      "participant_id": "Clara Ibrahim",
      "source_type": "synthetic_pilot",
      "age": "20",
      "gender": "Female",
      "student_status": "High school",
      "region": "Europe",
      "loneliness_score": "50.0",
      "social_connection_score": "66.7",
      "immediate_reward_bias": "16.7",
      "impulsive_spending_score": "25.0",
      "high_risk_choice_score": "20.0",
      "conflict_defense_score": "30.0",
      "risk_decision_index": "21.6",
      "decision_type": "Social-buffered deliberator"
    },
    {
      "participant_id": "Emma Garcia",
      "source_type": "synthetic_pilot",
      "age": "18",
      "gender": "Female",
      "student_status": "Undergraduate",
      "region": "North America",
      "loneliness_score": "60.7",
      "social_connection_score": "62.5",
      "immediate_reward_bias": "66.7",
      "impulsive_spending_score": "65.0",
      "high_risk_choice_score": "40.0",
      "conflict_defense_score": "25.0",
      "risk_decision_index": "53.3",
      "decision_type": "Balanced decision-maker"
    },
    {
      "participant_id": "Hannah Rossi",
      "source_type": "synthetic_pilot",
      "age": "16",
      "gender": "Male",
      "student_status": "High school",
      "region": "North America",
      "loneliness_score": "82.1",
      "social_connection_score": "79.2",
      "immediate_reward_bias": "33.3",
      "impulsive_spending_score": "55.0",
      "high_risk_choice_score": "20.0",
      "conflict_defense_score": "70.0",
      "risk_decision_index": "40.9",
      "decision_type": "Conflict-defensive responder"
    },
    {
      "participant_id": "Noah Tan",
      "source_type": "synthetic_pilot",
      "age": "19",
      "gender": "Male",
      "student_status": "High school",
      "region": "North America",
      "loneliness_score": "60.7",
      "social_connection_score": "41.7",
      "immediate_reward_bias": "33.3",
      "impulsive_spending_score": "35.0",
      "high_risk_choice_score": "20.0",
      "conflict_defense_score": "55.0",
      "risk_decision_index": "33.7",
      "decision_type": "Balanced decision-maker"
    },
    {
      "participant_id": "Nina Mehta",
      "source_type": "synthetic_pilot",
      "age": "18",
      "gender": "Female",
      "student_status": "High school",
      "region": "North America",
      "loneliness_score": "50.0",
      "social_connection_score": "62.5",
      "immediate_reward_bias": "50.0",
      "impulsive_spending_score": "70.0",
      "high_risk_choice_score": "40.0",
      "conflict_defense_score": "80.0",
      "risk_decision_index": "57.0",
      "decision_type": "Conflict-defensive responder"
    },
    {
      "participant_id": "Hannah Morgan",
      "source_type": "synthetic_pilot",
      "age": "22",
      "gender": "Female",
      "student_status": "Undergraduate",
      "region": "North America",
      "loneliness_score": "53.6",
      "social_connection_score": "79.2",
      "immediate_reward_bias": "0.0",
      "impulsive_spending_score": "20.0",
      "high_risk_choice_score": "80.0",
      "conflict_defense_score": "40.0",
      "risk_decision_index": "31.0",
      "decision_type": "Social-buffered deliberator"
    },
    {
      "participant_id": "Ella Evans",
      "source_type": "synthetic_pilot",
      "age": "20",
      "gender": "Nonbinary/Other",
      "student_status": "High school",
      "region": "Europe",
      "loneliness_score": "96.4",
      "social_connection_score": "45.8",
      "immediate_reward_bias": "83.3",
      "impulsive_spending_score": "85.0",
      "high_risk_choice_score": "60.0",
      "conflict_defense_score": "60.0",
      "risk_decision_index": "74.4",
      "decision_type": "Reward-sensitive accelerator"
    }
  ],
  "live": []
}